packaging_tutorial_rambasnet/__init__.py
packaging_tutorial_rambasnet/example.py
packaging_tutorial_rambasnet/tests/test_example.py
packaging_tutorial_rambasnet-0.0.1.dist-info/LICENSE
packaging_tutorial_rambasnet-0.0.1.dist-info/METADATA
packaging_tutorial_rambasnet-0.0.1.dist-info/WHEEL
packaging_tutorial_rambasnet-0.0.1.dist-info/RECORD
